{
  "date": "2026-06-04",
  "douyin_hot": [
    {
      "title": "NBA总决赛G1尼克斯胜马刺",
      "hot": "11942198"
    },
    {
      "title": "今晚油价将调整",
      "hot": "11659768"
    },
    {
      "title": "物流业景气指数重回扩张区间",
      "hot": "10586326"
    },
    {
      "title": "当我突然开始迷上擂茶",
      "hot": "9489611"
    },
    {
      "title": "用一篇长文记录我的高考",
      "hot": "8767767"
    },
    {
      "title": "高考安检新变化",
      "hot": "8722263"
    },
    {
      "title": "中国男篮战胜塞尔维亚FMP",
      "hot": "7705058"
    },
    {
      "title": "淡人专属夏季防晒穿搭",
      "hot": "7702701"
    },
    {
      "title": "苏式绿豆汤到底是什么味",
      "hot": "7679337"
    },
    {
      "title": "2026年全国高考报名人数1290万",
      "hot": "7675316"
    },
    {
      "title": "中国足球小将发长文致谢",
      "hot": "7668375"
    },
    {
      "title": "一人一句接唱为高考加油",
      "hot": "7662123"
    },
    {
      "title": "大睡特睡能修复大脑吗",
      "hot": "7659689"
    },
    {
      "title": "问你到底爱我有几分",
      "hot": "7658063"
    },
    {
      "title": "足球小将李昊炎加盟拉玛西亚",
      "hot": "7657657"
    },
    {
      "title": "麦子黄了 该回家啦",
      "hot": "7655096"
    },
    {
      "title": "看翘楚根本舍不得开倍速",
      "hot": "7654449"
    },
    {
      "title": "这个夏天的凉爽是冬瓜给的",
      "hot": "7646361"
    },
    {
      "title": "高考生我们为你护航",
      "hot": "7641679"
    },
    {
      "title": "菲律宾落选安理会非常任理事国",
      "hot": "7639702"
    },
    {
      "title": "脚艺人正式进军厨艺界",
      "hot": "7637963"
    },
    {
      "title": "这是谁的旅游运",
      "hot": "7637294"
    },
    {
      "title": "哈兰德领衔挪威队出征世界杯",
      "hot": "7635385"
    },
    {
      "title": "王橹杰海边金发氛围感",
      "hot": "7634309"
    },
    {
      "title": "回顾胡静怡过去的一年",
      "hot": "7633442"
    },
    {
      "title": "satisfaction方言挑战",
      "hot": "7631838"
    },
    {
      "title": "喜欢你6开播就又争又抢",
      "hot": "7630477"
    },
    {
      "title": "唐僧骑马太上头了",
      "hot": "7627870"
    },
    {
      "title": "短袖衬衫才是夏日的美妙单品",
      "hot": "7625639"
    },
    {
      "title": "微胖女孩的入夏藏肉穿搭",
      "hot": "7623902"
    },
    {
      "title": "歌手2026联名赛嘉宾匹配预测",
      "hot": "7621717"
    },
    {
      "title": "用方言给哈利波特片段配音",
      "hot": "7620037"
    },
    {
      "title": "奚梦瑶婚礼vlog随机掉落",
      "hot": "7618896"
    },
    {
      "title": "德国队进城打工穿搭风",
      "hot": "7618764"
    },
    {
      "title": "世界杯出征排面这一块",
      "hot": "7615898"
    },
    {
      "title": "于毅赵恒之吐槽赵吏",
      "hot": "7612062"
    },
    {
      "title": "陈都灵周翊然官配发力了",
      "hot": "7611742"
    },
    {
      "title": "我的进城办事专T来了",
      "hot": "7611654"
    },
    {
      "title": "来新疆感受别样异域风情",
      "hot": "7611008"
    },
    {
      "title": "琵琶行里的中式穿搭美学",
      "hot": "7608648"
    },
    {
      "title": "灵魂摆渡十年首播观后感",
      "hot": "7608038"
    },
    {
      "title": "用水瓶转场打开世界杯",
      "hot": "7578696"
    },
    {
      "title": "曾沛慈用0秒混入便利贴三人组",
      "hot": "7562522"
    },
    {
      "title": "黄灿灿是怎么说服陈瑶拍这个的",
      "hot": "7505815"
    },
    {
      "title": "穿adi办das",
      "hot": "7495263"
    },
    {
      "title": "游泳比赛萌娃自信pose亮了",
      "hot": "7445192"
    },
    {
      "title": "坐洛阳三轮车情绪价值拉满",
      "hot": "7440000"
    },
    {
      "title": "姜乘澜手把手教你鼻子修容",
      "hot": "7361930"
    },
    {
      "title": "这口洋芋泥螺蛳粉夯爆了",
      "hot": "7337933"
    },
    {
      "title": "老钱风怎么又火了",
      "hot": "7337359"
    }
  ],
  "topics": [
    {
      "topic": "苹果实况你要毁了小猫",
      "platform": "微博",
      "pattern": "呼告式拟人化",
      "content_type": "UGC",
      "insight": "「你要毁了XX」拟人喊话式产品吐槽——把功能缺陷包装成对「人」的道德谴责，比「XX功能太烂」传播力强10倍。动词「毁」降维打击=网感爆炸"
    },
    {
      "topic": "2188元一碗面日均卖出几十碗",
      "platform": "微博",
      "pattern": "数字驱动+反差",
      "content_type": "媒体首发→UGC",
      "insight": "双重数字冲突=天然辩论场。2188(天价) vs 日均几十碗(畅销)互相矛盾制造天然站队。一句话两个数字=极致信息密度，不需任何观点引导"
    },
    {
      "topic": "地球online穿模了",
      "platform": "微博",
      "pattern": "概念迁徙",
      "content_type": "100%UGC",
      "insight": "游戏术语「穿模」社会化=圈层黑话大众化新范式。「地球online」把现实重新框架为游戏=世界观重新定义。话题下网友接力玩梗(钱包穿模/建议2.0补丁)"
    },
    {
      "topic": "日本超市货架正在失去颜色",
      "platform": "微博",
      "pattern": "画面呈现+陌生化比喻",
      "content_type": "媒体/KOL首发",
      "insight": "「正在失去颜色」=诗化表达替代「经济衰退」。视觉比喻暗示而非直接陈述，「颜色」代指繁荣=高度文学化。进行时态「正在」增加时间紧迫感"
    },
    {
      "topic": "苹果输入法你上过学没有",
      "platform": "微博",
      "pattern": "呼告式AI吐槽体",
      "content_type": "UGC",
      "insight": "延续「豆包豆包帮我把这群智障删掉」范式——直接对产品质问学历。「上过学没有」>「太蠢了」=画面感爆表。AI产品吐槽已成稳定热搜输出管道"
    },
    {
      "topic": "当我突然开始迷上擂茶",
      "platform": "抖音",
      "pattern": "UGC触发器",
      "content_type": "100%UGC",
      "insight": "「当我XX」触发器第六次验证。「突然开始迷上」=个人顿悟+时间递进双重钩子。传统食物(擂茶)新包装=文化复苏型传播"
    },
    {
      "topic": "这个夏天的凉爽是冬瓜给的",
      "platform": "抖音",
      "pattern": "神比喻",
      "content_type": "UGC",
      "insight": "「XX是XX给的」感恩句式+荒诞对象=反差萌天花板。不直接说「冬瓜能解暑」而是「凉爽=冬瓜的功劳」=食物拟人化。神比喻>功能陈述"
    },
    {
      "topic": "脚艺人正式进军厨艺界",
      "platform": "抖音",
      "pattern": "概念迁徙",
      "content_type": "UGC",
      "insight": "「正式进军XX界」用正经宣布口吻讲荒诞跨界=假装严肃的幽默。「脚艺人」标签化无需解释。跨界宣布体=可预测更多填充物"
    }
  ],
  "net_sense": [
    {
      "source": "苹果实况你要毁了小猫",
      "platform": "微博",
      "insight": "「你要毁了XX」拟人喊话句式——把产品/功能不满包装成对具体人的指责。动词「毁」=降维打击，比「太烂了」高级10倍"
    },
    {
      "source": "2188元一碗面日均卖出几十碗",
      "platform": "微博",
      "insight": "双重数字冲突=天然辩论场。15字塞入两个矛盾数字，不需观点引导，数字本身制造站队"
    },
    {
      "source": "地球online穿模了",
      "platform": "微博",
      "insight": "游戏术语社会化新范式——「穿模」替代「异常」「bug」=圈层黑话→大众表达。「地球online」世界观框架=重新定义现实"
    },
    {
      "source": "苹果输入法你上过学没有",
      "platform": "微博",
      "insight": "AI产品吐槽标准化——质问产品学历>说产品笨。「XX你上过学没有」=新吐槽范式，比「豆包豆包帮我删掉智障」更简洁直接"
    },
    {
      "source": "这个夏天的凉爽是冬瓜给的",
      "platform": "抖音",
      "insight": "「XX是XX给的」感恩荒诞句式——正经感恩+荒诞对象=反差萌。食物拟人化新高度，比功能陈述传播力强10倍"
    },
    {
      "source": "脚艺人正式进军厨艺界",
      "platform": "抖音",
      "insight": "「正式进军XX界」跨界宣布体——假装严肃的幽默。「脚艺人」三字标签化=极致压缩，可预测更多行业跨界梗"
    }
  ],
  "learnings": [
    "【微博新范式①】「你要毁了XX」拟人喊话——产品吐槽进化从「XX功能太烂」→「XX你要毁了小猫」，拟人化+动词降维=网感指数增长。适用所有产品/功能吐槽场景",
    "【微博新范式②】双重数字冲突=天然辩论场——「2188元一碗面日均卖出几十碗」，两个矛盾数字15字内制造天然站队。不需要任何情绪引导词，数字自己会吵架",
    "【微博新范式③】「地球online」游戏框架——用游戏世界观重新解释现实异常，「穿模」替代「异常」。圈层术语完成大众化迁移=游戏黑话热搜化的标准路径",
    "【抖音新范式①】「XX是XX给的」感恩荒诞句式——用正式感恩句式搭配荒诞对象。「凉爽是冬瓜给的」=食物拟人化新高度",
    "【抖音新范式②】「正式进军XX界」跨界宣布体——假装严肃的幽默+标签化身份。「脚艺人」三字=所有信息，可预测更多跨界玩梗",
    "【跨平台①】高考节点分发固化——抖音3条高考上榜(长文记录/安检变化/1290万报名)，微博零高考。抖音对节点正能量传播效率继续碾压微博",
    "【跨平台②】体育话题两平台均上榜——抖音走赛果直述(NBA总决赛G1尼克斯胜马刺)，微博走戏剧化事件(球迷冲场)。角度分化规律持续验证",
    "【跨平台③】美食话题分化——抖音尾段7条地方美食(擂茶/绿豆汤/洋芋螺蛳粉夯爆了等)，微博仅天价面(高冲突定价争议)。美食在微博需冲突钩子",
    "【亮点1】拟人化喊话已成微博吐槽新标准——从豆包到苹果实况到苹果输入法，直接对话产品的句式成为稳定热搜输出管道",
    "【亮点2】「地球online」=游戏术语大众化教科书——穿模→现实bug的翻译比「异常」「罕见」好10倍。游戏圈层黑话正在成为全民表达",
    "【亮点3】抖音「XX是XX给的」=万能感恩荒诞模板——凉爽是冬瓜给的/快乐是奶茶给的/青春是校服给的=可无限填充",
    "【亮点4】双重数字冲突=标题自动生成器——天价数字+反常数据=不需任何加工即成热搜。今日最值钱的标题公式"
  ],
  "hot_list": [
    {
      "title": "100秒看大国外交的繁忙五月",
      "hot": ""
    },
    {
      "title": "中国不存在所谓强迫劳动",
      "hot": ""
    },
    {
      "title": "NBA总决赛球迷冲场",
      "hot": ""
    },
    {
      "title": "每一次突破见证中国基建实力",
      "hot": ""
    },
    {
      "title": "平均睡眠7小时却3年出现2次脑梗",
      "hot": ""
    },
    {
      "title": "苹果实况你要毁了小猫",
      "hot": ""
    },
    {
      "title": "租房遇见这空调天塌了",
      "hot": ""
    },
    {
      "title": "2188元一碗面日均卖出几十碗",
      "hot": ""
    },
    {
      "title": "家业没破万",
      "hot": ""
    },
    {
      "title": "曝VisionPro产品线被移除",
      "hot": ""
    },
    {
      "title": "杨紫吐槽横店怎么会有这么多坏马",
      "hot": ""
    },
    {
      "title": "地球online穿模了",
      "hot": ""
    },
    {
      "title": "韩栋直播哭诉没戏拍",
      "hot": ""
    },
    {
      "title": "顾客被张雪店员教唆偷开无牌照机车",
      "hot": ""
    },
    {
      "title": "尼克斯1比0马刺",
      "hot": ""
    },
    {
      "title": "杨洋曾想整鼻子",
      "hot": ""
    },
    {
      "title": "当章若楠发现主持人的裙子有点短",
      "hot": ""
    },
    {
      "title": "女子买验孕笔用后仅退款还嘲讽商家",
      "hot": ""
    },
    {
      "title": "杨紫扛剧能力",
      "hot": ""
    },
    {
      "title": "日本超市货架正在失去颜色",
      "hot": ""
    },
    {
      "title": "中国机器人亮相美国达人秀",
      "hot": ""
    },
    {
      "title": "奚梦瑶晒照感谢婆婆",
      "hot": ""
    },
    {
      "title": "iPhone18Pro八大亮点",
      "hot": ""
    },
    {
      "title": "法国女孩头痛多年在中国找到病因",
      "hot": ""
    },
    {
      "title": "飞机上偶遇张凌赫睡觉",
      "hot": ""
    },
    {
      "title": "iPhone18ProMax实测厚度8.75mm",
      "hot": ""
    },
    {
      "title": "奚梦瑶家境",
      "hot": ""
    },
    {
      "title": "小英都变张元英了",
      "hot": ""
    },
    {
      "title": "注会师跳槽甲方10个月赚6000万",
      "hot": ""
    },
    {
      "title": "家业 版权剧",
      "hot": ""
    },
    {
      "title": "向太自曝房产只写了自己名字",
      "hot": ""
    },
    {
      "title": "12岁男孩一顿半斤肉体重200斤",
      "hot": ""
    },
    {
      "title": "忆秦娥舞台坍塌砸死孩子",
      "hot": ""
    },
    {
      "title": "灵魂摆渡十年孕妇故事大反转",
      "hot": ""
    },
    {
      "title": "苹果输入法你上过学没有",
      "hot": ""
    },
    {
      "title": "虞书欣双轨海外热度超过许我耀眼",
      "hot": ""
    },
    {
      "title": "NBA总决赛",
      "hot": ""
    },
    {
      "title": "国企干部离婚分割近亿财产当严查",
      "hot": ""
    },
    {
      "title": "翘楚单更",
      "hot": ""
    },
    {
      "title": "6月桃花运最旺的星座",
      "hot": ""
    },
    {
      "title": "恋综男嘉宾撞脸朴海镇",
      "hot": ""
    },
    {
      "title": "正脸和侧脸的差别能有多大",
      "hot": ""
    },
    {
      "title": "周迅朴叙俊金高银同框",
      "hot": ""
    },
    {
      "title": "王嘉尔何猷君跳舞",
      "hot": ""
    },
    {
      "title": "李昊炎加盟巴萨",
      "hot": ""
    },
    {
      "title": "菲律宾落选安理会非常任理事国",
      "hot": ""
    },
    {
      "title": "歌手第三期歌单",
      "hot": ""
    },
    {
      "title": "胡三元 老年痴呆",
      "hot": ""
    },
    {
      "title": "去图书馆太频繁的后果",
      "hot": ""
    },
    {
      "title": "尼克斯vs马刺",
      "hot": ""
    },
    {
      "title": "泽连斯基称愿即刻与普京直接谈判",
      "hot": ""
    }
  ],
  "case_library": [
    {
      "date": "0604",
      "source": "苹果实况你要毁了小猫",
      "insight": "「你要毁了XX」拟人喊话式产品吐槽——把功能缺陷包装成对具体人的道德谴责。动词「毁」=降维打击"
    },
    {
      "date": "0604",
      "source": "地球online穿模了",
      "insight": "游戏术语社会化——「穿模」替代「异常」=圈层黑话→大众表达。「地球online」世界观框架重新定义现实"
    },
    {
      "date": "0604",
      "source": "这个夏天的凉爽是冬瓜给的",
      "insight": "「XX是XX给的」感恩荒诞句式——正经感恩+荒诞对象=反差萌天花板"
    },
    {
      "date": "0604",
      "source": "脚艺人正式进军厨艺界",
      "insight": "「正式进军XX界」跨界宣布体——假装严肃的幽默+三字标签化"
    }
  ]
}